zohocrmsdk/__init__.py
zohocrmsdk/src/__init__.py
zohocrmsdk/src/json_details.json
zohocrmsdk/src/com/__init__.py
zohocrmsdk/src/com/zoho/__init__.py
zohocrmsdk/src/com/zoho/api/__init__.py
zohocrmsdk/src/com/zoho/api/authenticator/__init__.py
zohocrmsdk/src/com/zoho/api/authenticator/oauth_token.py
zohocrmsdk/src/com/zoho/api/authenticator/token.py
zohocrmsdk/src/com/zoho/api/authenticator/store/__init__.py
zohocrmsdk/src/com/zoho/api/authenticator/store/db_store.py
zohocrmsdk/src/com/zoho/api/authenticator/store/file_store.py
zohocrmsdk/src/com/zoho/api/authenticator/store/token_store.py
zohocrmsdk/src/com/zoho/api/logger/__init__.py
zohocrmsdk/src/com/zoho/api/logger/logger.py
zohocrmsdk/src/com/zoho/crm/__init__.py
zohocrmsdk/src/com/zoho/crm/api/__init__.py
zohocrmsdk/src/com/zoho/crm/api/header.py
zohocrmsdk/src/com/zoho/crm/api/header_map.py
zohocrmsdk/src/com/zoho/crm/api/initializer.py
zohocrmsdk/src/com/zoho/crm/api/param.py
zohocrmsdk/src/com/zoho/crm/api/parameter_map.py
zohocrmsdk/src/com/zoho/crm/api/request_proxy.py
zohocrmsdk/src/com/zoho/crm/api/sdk_config.py
zohocrmsdk/src/com/zoho/crm/api/user_signature.py
zohocrmsdk/src/com/zoho/crm/api/apis/__init__.py
zohocrmsdk/src/com/zoho/crm/api/apis/api_exception.py
zohocrmsdk/src/com/zoho/crm/api/apis/apis_operations.py
zohocrmsdk/src/com/zoho/crm/api/apis/operation_types.py
zohocrmsdk/src/com/zoho/crm/api/apis/response_handler.py
zohocrmsdk/src/com/zoho/crm/api/apis/response_wrapper.py
zohocrmsdk/src/com/zoho/crm/api/apis/supported_api.py
zohocrmsdk/src/com/zoho/crm/api/appointment_preference/__init__.py
zohocrmsdk/src/com/zoho/crm/api/appointment_preference/action_handler.py
zohocrmsdk/src/com/zoho/crm/api/appointment_preference/action_response.py
zohocrmsdk/src/com/zoho/crm/api/appointment_preference/action_wrapper.py
zohocrmsdk/src/com/zoho/crm/api/appointment_preference/api_exception.py
zohocrmsdk/src/com/zoho/crm/api/appointment_preference/appointment_preference.py
zohocrmsdk7_0-6.0.0.dist-info/LICENSE
zohocrmsdk7_0-6.0.0.dist-info/METADATA
zohocrmsdk7_0-6.0.0.dist-info/WHEEL
zohocrmsdk7_0-6.0.0.dist-info/top_level.txt
zohocrmsdk7_0-6.0.0.dist-info/RECORD
