Metadata-Version: 2.1
Name: zohocrmsdk7-0
Version: 6.0.0
Summary: Zoho CRM SDK for ZOHO CRM v7 APIs
Home-page: https://github.com/zoho/zohocrm-python-sdk-7.0
Author: Zoho CRM API Team
Author-email: support@zohocrm.com
License: Apache Software License, Version 2.0, http://www.apache.org/licenses/LICENSE-2.0
Keywords: development,zoho,crm,api,zcrmsdk,zohocrmsdksdk,zcrm,zohocrmsdk7_0
Platform: UNKNOWN
Classifier: Development Status :: 5 - Production/Stable
Classifier: Intended Audience :: Developers
Classifier: License :: OSI Approved :: Apache Software License
Classifier: Topic :: Software Development :: Build Tools
Classifier: Programming Language :: Python :: 3
Classifier: Programming Language :: Python :: 3.3
Classifier: Programming Language :: Python :: 3.4
Classifier: Programming Language :: Python :: 3.5
Classifier: Programming Language :: Python :: 3.6
Classifier: Programming Language :: Python :: 3.7
Classifier: Programming Language :: Python :: 3.8
License-File: LICENSE
Requires-Dist: requests
Requires-Dist: python-dateutil
Requires-Dist: urllib3
Requires-Dist: mysql-connector-python
Requires-Dist: setuptools
